evoproc/__init__.py
evoproc/ga_scaffold_structured.py
evoproc/helpers.py
evoproc/models.py
evoproc/scorers.py
evoproc/validators.py
evoproc-1.0.0.dist-info/METADATA
evoproc-1.0.0.dist-info/WHEEL
evoproc-1.0.0.dist-info/top_level.txt
evoproc-1.0.0.dist-info/RECORD
