Metadata-Version: 2.4
Name: evoproc
Version: 1.0.0
Summary: EvoProc: genetic algorithm scaffold for evolving LLM-generated procedures
Author: Malia Barker
License: MIT
Project-URL: Homepage, https://github.com/<you>/<repo>
Project-URL: Documentation, https://<your-docs-site>
Project-URL: Source, https://github.com/<you>/<repo>
Project-URL: Issues, https://github.com/<you>/<repo>/issues
Keywords: llm,genetic-algorithm,reasoning,procedures,evolution
Requires-Python: >=3.10
